mlspeclib/__init__.py
mlspeclib/_version.py
mlspeclib/core.py
mlspeclib/helpers.py
mlspeclib/io.py
mlspeclib/mlobject.py
mlspeclib/mlschema.py
mlspeclib/mlschemaenums.py
mlspeclib/mlschemafields.py
mlspeclib/mlschemavalidators.py
mlspeclib/experimental/__init__.py
mlspeclib/experimental/github.py
mlspeclib/experimental/gremlin_helpers.py
mlspeclib/experimental/metastore.py
mlspeclib/schemas/0/0/1/base.yaml
mlspeclib/schemas/0/0/1/container_store.yaml
mlspeclib/schemas/0/0/1/conversion.yaml
mlspeclib/schemas/0/0/1/datapath.yaml
mlspeclib/schemas/0/0/1/dataschema.yaml
mlspeclib/schemas/0/0/1/datasource.yaml
mlspeclib/schemas/0/0/1/environment.yml
mlspeclib/schemas/0/0/1/metadata.yaml
mlspeclib/schemas/0/0/1/model.yaml
mlspeclib/schemas/0/0/1/runconfig.yaml
mlspeclib/schemas/0/0/1/score.yaml
mlspeclib/schemas/0/0/1/serve.yaml
mlspeclib/schemas/0/0/1/train_execution.yaml
mlspeclib/schemas/0/0/1/train_results.yaml
mlspeclib/schemas/0/0/1/training_post_process.yaml
mlspeclib/schemas/0/0/1/workflow.yaml
mlspeclib/schemas/0/0/1/zdata_version_control.yaml
mlspeclib/schemas/0/0/1/workflow_schemas/data_process_run.yaml
mlspeclib/schemas/0/0/1/workflow_schemas/data_result.yaml
mlspeclib/schemas/0/0/1/workflow_schemas/data_source.yaml
mlspeclib/schemas/0/0/1/workflow_schemas/package_result.yaml
mlspeclib/schemas/0/0/1/workflow_schemas/package_run.yaml
mlspeclib/schemas/0/0/1/workflow_schemas/training_results.yaml
mlspeclib/schemas/0/0/1/workflow_schemas/training_run.yaml
mlspeclib/schemas/0/1/0/base.yaml
mlspeclib/schemas/0/1/0/component.yaml
mlspeclib/schemas/0/1/0/environment.yaml
mlspeclib/schemas/0/1/0/job.yaml
mlspeclib/schemas/0/1/0/log.yaml
mlspeclib-1.1.15.dist-info/LICENSE
mlspeclib-1.1.15.dist-info/METADATA
mlspeclib-1.1.15.dist-info/WHEEL
mlspeclib-1.1.15.dist-info/top_level.txt
mlspeclib-1.1.15.dist-info/RECORD
