Metadata-Version: 2.1
Name: mlspeclib
Version: 1.1.15
Summary: MLSpec helper library makes using metadata in ML workflows easier.
Home-page: https://github.com/mlspec/mlspec-lib
Author: David Aronchick
Author-email: aronchick@gmail.com
License: MIT License
Keywords: MLSpec,Machine Learning
Platform: UNKNOWN
Classifier: Development Status :: 4 - Beta
Classifier: Intended Audience :: Developers
Classifier: Topic :: Software Development :: Build Tools
Classifier: License :: OSI Approved :: MIT License
Classifier: Programming Language :: Python :: 3
Classifier: Programming Language :: Python :: 3.4
Classifier: Programming Language :: Python :: 3.5
Classifier: Programming Language :: Python :: 3.6
License-File: LICENSE
Requires-Dist: wheel
Requires-Dist: pyyaml
Requires-Dist: marshmallow
Requires-Dist: uritools
Requires-Dist: semver
Requires-Dist: python-box
Requires-Dist: gremlinpython
Requires-Dist: pymysql
Requires-Dist: gitpython
